PIFuHD/__init__.py
PIFuHD/__main__.py
PIFuHD/colab_util.py
PIFuHD/evaluator.py
PIFuHD/geometry.py
PIFuHD/mesh_util.py
PIFuHD/net_util.py
PIFuHD/networks.py
PIFuHD/options.py
PIFuHD/recontructor.py
PIFuHD/sdf.py
PIFuHD/data/EvalDataset.py
PIFuHD/data/EvalWMetaDataset.py
PIFuHD/data/EvalWPoseDataset.py
PIFuHD/data/EvalWRectDataset.py
PIFuHD/data/ImageBundle.py
PIFuHD/data/__init__.py
PIFuHD/data/helper_dataset.py
PIFuHD/data/helper_image_crop.py
PIFuHD/model/BasePIFuNet.py
PIFuHD/model/DepthNormalizer.py
PIFuHD/model/HGFilters.py
PIFuHD/model/HGPIFuMRNet.py
PIFuHD/model/HGPIFuNetwNML.py
PIFuHD/model/MLP.py
PIFuHD/model/__init__.py
PIFuHD/render/__init__.py
PIFuHD/render/camera.py
PIFuHD/render/glm.py
PIFuHD/render/mesh.py
PIFuHD/render/gl/__init__.py
PIFuHD/render/gl/cam_render.py
PIFuHD/render/gl/color_render.py
PIFuHD/render/gl/framework.py
PIFuHD/render/gl/geo_render.py
PIFuHD/render/gl/normal_render.py
PIFuHD/render/gl/render.py
pifu_hd-1.0.1.dist-info/LICENSE
pifu_hd-1.0.1.dist-info/METADATA
pifu_hd-1.0.1.dist-info/WHEEL
pifu_hd-1.0.1.dist-info/entry_points.txt
pifu_hd-1.0.1.dist-info/top_level.txt
pifu_hd-1.0.1.dist-info/RECORD
