Metadata-Version: 2.1
Name: pifu-hd
Version: 1.0.1
Summary: PIFuHD: Multi-Level Pixel-Aligned Implicit Function for High-Resolution 3D Human Digitization (CVPR 2020)
Home-page: https://github.com/facebookresearch/pifuhd
Author: Shunsuke Saito
Author-email: shunsuke.saito16@gmail.com
License: Creative Commons
Classifier: Development Status :: 5 - Production/Stable
Classifier: Intended Audience :: Developers
Classifier: Intended Audience :: Science/Research
Classifier: Natural Language :: English
Classifier: Operating System :: OS Independent
Classifier: Programming Language :: Python
Classifier: Programming Language :: Python :: 3.5
Classifier: Programming Language :: Python :: 3.6
Classifier: Programming Language :: Python :: 3.7
Classifier: Programming Language :: Python :: 3.8
Classifier: Programming Language :: Python :: 3.9
Classifier: Programming Language :: Python :: 3 :: Only
License-File: LICENSE
Requires-Dist: torch
Requires-Dist: torchvision
Requires-Dist: Pillow
Requires-Dist: scikit-image
Requires-Dist: tqdm
Requires-Dist: opencv-python
Requires-Dist: trimesh
Requires-Dist: PyOpenGL
Requires-Dist: ffmpeg
